codino/__init__.py
codino/data/AminoAcidTable.py
codino/data/CodonDesign.py
codino/data/CodonTable.py
codino/data/FreqTable.py
codino/data/__init__.py
codino/process/Converter.py
codino/process/__init__.py
codino-0.1.1.dist-info/LICENSE
codino-0.1.1.dist-info/WHEEL
codino-0.1.1.dist-info/METADATA
codino-0.1.1.dist-info/RECORD
