Metadata-Version: 2.1
Name: codino
Version: 0.1.1
Summary: Calculating amino acid frequencies from codon design, and vice versa
License: MIT
Author: David Zhang
Requires-Python: >=3.8,<4.0
Classifier: License :: OSI Approved :: MIT License
Classifier: Programming Language :: Python :: 3
Classifier: Programming Language :: Python :: 3.8
Classifier: Programming Language :: Python :: 3.9
